webup/VERSION
webup/__init__.py
webup/cache_control.py
webup/content_type.py
webup/files.py
webup/py.typed
webup/queue.py
webup/session.py
webup/ssm.py
webup/suffix.py
webup/upload_process.py
webup/models/__init__.py
webup/models/file.py
webup/models/output.py
webup/models/py.typed
webup/models/upload_result.py
webup-2.0.0.dist-info/LICENSE
webup-2.0.0.dist-info/METADATA
webup-2.0.0.dist-info/WHEEL
webup-2.0.0.dist-info/top_level.txt
webup-2.0.0.dist-info/RECORD
